{"assets":{"BE27CFED30023A25174C01549F881949":{"type":"texture","index":40,"assetRequest":{"type":"slide","state":"incoming","slide":"79B281D5-A072-43CC-90F7-4CD4CD6DABBF"},"url":"assets/BE27CFED30023A25174C01549F881949.svg","width":1024,"height":768},"1BD2835E22F9C6F1FD62E8522C32F9D7":{"type":"texture","index":35,"assetRequest":{"type":"slide","state":"contents","slide":"CFA82BD5-2C02-4F85-8506-3C83E7961AA4"},"url":"assets/1BD2835E22F9C6F1FD62E8522C32F9D7.svg","width":966,"height":764},"03E2A4267C1077634D56A7B4FCEDB452":{"type":"texture","index":37,"assetRequest":{"type":"slide","state":"contents","slide":"CFA82BD5-2C02-4F85-8506-3C83E7961AA4"},"url":"assets/03E2A4267C1077634D56A7B4FCEDB452.svg","width":285,"height":518},"07BB6D00D518A96220A4FC58EE8BCBF4":{"type":"texture","index":38,"assetRequest":{"type":"slide","state":"contents","slide":"CFA82BD5-2C02-4F85-8506-3C83E7961AA4"},"url":"assets/07BB6D00D518A96220A4FC58EE8BCBF4.svg","width":186,"height":113},"0B7E82647FE32B8434637900C863EBF3":{"type":"texture","index":39,"assetRequest":{"type":"slide","state":"outgoing","slide":"CFA82BD5-2C02-4F85-8506-3C83E7961AA4"},"url":"assets/0B7E82647FE32B8434637900C863EBF3.svg","width":1024,"height":768},"8414E3B013F9A5AA6A3E085AE0F7E849":{"type":"texture","index":34,"assetRequest":{"type":"slide","state":"contents","slide":"CFA82BD5-2C02-4F85-8506-3C83E7961AA4"},"url":"assets/8414E3B013F9A5AA6A3E085AE0F7E849.svg","width":1073,"height":836},"0708201BFD57950854BA39BE36670832":{"type":"texture","index":36,"assetRequest":{"type":"slide","state":"contents","slide":"CFA82BD5-2C02-4F85-8506-3C83E7961AA4"},"url":"assets/0708201BFD57950854BA39BE36670832.svg","width":487,"height":292},"498E23C82CA78A4BCD7BA88E5243B6FC":{"type":"texture","index":33,"assetRequest":{"type":"slide","state":"contents","slide":"CFA82BD5-2C02-4F85-8506-3C83E7961AA4"},"url":"assets/498E23C82CA78A4BCD7BA88E5243B6FC.svg","width":1024,"height":768}},"events":[{"effects":[{"beginTime":0,"baseLayer":{"animations":[],"initialState":{"affineTransform":[1,0,0,1,0,0],"masksToBounds":false,"rotation":0,"scale":1,"position":{"pointX":253.1645812988281,"pointY":169.5929565429688},"width":484.3291015625,"sublayerTransform":[1,0,0,0,0,1,0,0,0,0,1,0,0,0,0,1],"contentsRect":{"y":0,"x":0,"width":1,"height":1},"opacity":1,"edgeAntialiasingMask":15,"height":289,"hidden":false,"anchorPoint":{"pointX":0.5,"pointY":0.5}},"objectID":"D8CE3AF1-87F9-403A-ABA6-263FDDBAB4F5","layers":[{"animations":[],"initialState":{"affineTransform":[1,0,0,1,0,0],"masksToBounds":false,"rotation":0,"scale":1,"position":{"pointX":500.9999694824219,"pointY":358.9070434570312},"width":484.3291015625,"sublayerTransform":[1,0,0,0,0,1,0,0,0,0,1,-0.0004922987690640373,0,0,0,1],"contentsRect":{"y":0,"x":0,"width":1,"height":1},"opacity":1,"edgeAntialiasingMask":15,"height":289,"hidden":false,"anchorPoint":{"pointX":1.034420537329142,"pointY":1.241892883934364}},"layers":[{"animations":[{"repeatCount":0,"animations":[{"repeatCount":0,"timingControlPoint2y":1,"from":{"scalar":-3.141592653589793},"timingFunction":"custom","timingControlPoint1x":0.3953104317188263,"property":"transform.rotation.y","fillMode":"removed","duration":0.25,"beginTime":0,"timingControlPoint2x":0.3992834389209747,"timingControlPoint1y":0.004784102085977793,"to":{"scalar":0}},{"timingFunctions":[{"timingFunction":"custom","timingControlPoint1y":0,"timingControlPoint2x":0.3796900808811188,"timingControlPoint1x":0.6810944080352783,"timingControlPoint2y":0.9981408715248108},{"timingFunction":"linear"}],"values":[{"scalar":0},{"scalar":1},{"scalar":1}],"beginTime":0,"repeatCount":0,"keyTimes":[0,0.9,1],"property":"opacity","fillMode":"both","duration":0.25},{"from":{"scalar":false},"beginTime":0.0001,"repeatCount":0,"fillMode":"forwards","property":"hidden","duration":0.2499,"to":{"scalar":false}}],"beginTime":1e-100,"fillMode":"both","duration":0.25}],"layers":[],"initialState":{"affineTransform":[1,0,0,1,0,0],"masksToBounds":false,"rotation":0,"scale":1,"position":{"pointX":242.4999694824219,"pointY":144.9070434570312},"width":487,"sublayerTransform":[1,0,0,0,0,1,0,0,0,0,1,0,0,0,0,1],"contentsRect":{"y":0,"x":0,"width":1,"height":1},"opacity":1,"edgeAntialiasingMask":0,"height":292,"hidden":true,"anchorPoint":{"pointX":0.5,"pointY":0.5}},"texture":"0708201BFD57950854BA39BE36670832"}]}]},"effects":[{"beginTime":0,"baseLayer":{"animations":[],"initialState":{"affineTransform":[1,0,0,1,0,0],"masksToBounds":false,"rotation":0,"scale":1,"position":{"pointX":810.2232055664062,"pointY":494.1589050292969},"width":282,"sublayerTransform":[1,0,0,0,0,1,0,0,0,0,1,0,0,0,0,1],"contentsRect":{"y":0,"x":0,"width":1,"height":1},"opacity":1,"edgeAntialiasingMask":15,"height":515.6821899414062,"hidden":false,"anchorPoint":{"pointX":0.5,"pointY":0.5}},"objectID":"80067297-E7D8-4843-BC5E-F2976BBE1970","layers":[{"animations":[],"initialState":{"affineTransform":[1,0,0,1,0,0],"masksToBounds":false,"rotation":0,"scale":1,"position":{"pointX":-157.2232055664062,"pointY":147.6821899414062},"width":282,"sublayerTransform":[1,0,0,0,0,1,0,0,0,0,1,-0.0004922987690640373,0,0,0,1],"contentsRect":{"y":0,"x":0,"width":1,"height":1},"opacity":1,"edgeAntialiasingMask":15,"height":515.6821899414062,"hidden":false,"anchorPoint":{"pointX":-0.5575290977532137,"pointY":0.2863821803855325}},"layers":[{"animations":[{"repeatCount":0,"animations":[{"from":{"scalar":0},"beginTime":0,"repeatCount":0,"fillMode":"both","property":"opacity","duration":0.5,"timingFunction":"easeInEaseOut","to":{"scalar":1}},{"from":{"scalar":false},"beginTime":0,"repeatCount":0,"fillMode":"forwards","property":"hidden","duration":0.5,"to":{"scalar":false}}],"beginTime":1e-100,"fillMode":"both","duration":0.5}],"layers":[],"initialState":{"affineTransform":[1,0,0,1,0,0],"masksToBounds":false,"rotation":0,"scale":1,"position":{"pointX":141.2767944335938,"pointY":257.6821899414062},"width":285,"sublayerTransform":[1,0,0,0,0,1,0,0,0,0,1,0,0,0,0,1],"contentsRect":{"y":0,"x":0,"width":1,"height":1},"opacity":1,"edgeAntialiasingMask":0,"height":518,"hidden":true,"anchorPoint":{"pointX":0.5,"pointY":0.5}},"texture":"03E2A4267C1077634D56A7B4FCEDB452"}]}]},"effects":[],"duration":0.5,"type":"buildIn","attributes":{"direction":0},"name":"com.apple.iWork.Keynote.BUKAnvil","objectID":"80067297-E7D8-4843-BC5E-F2976BBE1970"}],"duration":0.25,"type":"buildIn","name":"apple:revolve","objectID":"D8CE3AF1-87F9-403A-ABA6-263FDDBAB4F5"}],"automaticPlay":true,"hyperlinks":[],"accessibility":[{"text":"VS","targetRectangle":{"y":329.5,"x":410.58837890625,"width":180,"height":126}}],"baseLayer":{"animations":[],"initialState":{"affineTransform":[1,0,0,1,0,0],"masksToBounds":true,"rotation":0,"scale":1,"position":{"pointX":512,"pointY":384},"width":1024,"sublayerTransform":[1,0,0,0,0,1,0,0,0,0,1,0,0,0,0,1],"contentsRect":{"y":0,"x":0,"width":1,"height":1},"opacity":1,"edgeAntialiasingMask":0,"height":768,"hidden":false,"anchorPoint":{"pointX":0.5,"pointY":0.5}},"layers":[{"animations":[],"initialState":{"affineTransform":[1,0,0,1,0,0],"masksToBounds":false,"rotation":0,"scale":1,"position":{"pointX":512,"pointY":384},"width":1024,"sublayerTransform":[1,0,0,0,0,1,0,0,0,0,1,0,0,0,0,1],"contentsRect":{"y":0,"x":0,"width":1,"height":1},"opacity":1,"edgeAntialiasingMask":15,"height":768,"hidden":false,"anchorPoint":{"pointX":0.5,"pointY":0.5}},"layers":[{"animations":[],"initialState":{"affineTransform":[1,0,0,1,0,0],"masksToBounds":false,"rotation":0,"scale":1,"position":{"pointX":512,"pointY":384},"width":1024,"sublayerTransform":[1,0,0,0,0,1,0,0,0,0,1,0,0,0,0,1],"contentsRect":{"y":0,"x":0,"width":1,"height":1},"opacity":1,"edgeAntialiasingMask":15,"height":768,"hidden":false,"anchorPoint":{"pointX":0.5,"pointY":0.5}},"layers":[{"animations":[],"layers":[],"initialState":{"affineTransform":[1,0,0,1,0,0],"masksToBounds":false,"rotation":0,"scale":1,"position":{"pointX":512,"pointY":384},"width":1024,"sublayerTransform":[1,0,0,0,0,1,0,0,0,0,1,0,0,0,0,1],"contentsRect":{"y":0,"x":0,"width":1,"height":1},"opacity":1,"edgeAntialiasingMask":0,"height":768,"hidden":false,"anchorPoint":{"pointX":0.5,"pointY":0.5}},"texture":"498E23C82CA78A4BCD7BA88E5243B6FC"}]}]},{"animations":[],"initialState":{"affineTransform":[1,0,0,1,0,0],"masksToBounds":false,"rotation":0,"scale":1,"position":{"pointX":512,"pointY":384},"width":1024,"sublayerTransform":[1,0,0,0,0,1,0,0,0,0,1,0,0,0,0,1],"contentsRect":{"y":0,"x":0,"width":1,"height":1},"opacity":1,"edgeAntialiasingMask":15,"height":768,"hidden":false,"anchorPoint":{"pointX":0.5,"pointY":0.5}},"layers":[{"animations":[],"initialState":{"affineTransform":[1,0,0,1,0,0],"masksToBounds":false,"rotation":0,"scale":1,"position":{"pointX":491.5,"pointY":355},"width":1071,"sublayerTransform":[1,0,0,0,0,1,0,0,0,0,1,0,0,0,0,1],"contentsRect":{"y":0,"x":0,"width":1,"height":1},"opacity":1,"edgeAntialiasingMask":15,"height":834,"hidden":false,"anchorPoint":{"pointX":0.5,"pointY":0.5}},"objectID":"4C07A087-55E8-4144-BA3C-1F583565FBDF","layers":[{"animations":[],"layers":[],"initialState":{"affineTransform":[1,0,0,1,0,0],"masksToBounds":false,"rotation":0,"scale":1,"position":{"pointX":535.5,"pointY":417},"width":1073,"sublayerTransform":[1,0,0,0,0,1,0,0,0,0,1,0,0,0,0,1],"contentsRect":{"y":0,"x":0,"width":1,"height":1},"opacity":1,"edgeAntialiasingMask":0,"height":836,"hidden":false,"anchorPoint":{"pointX":0.5,"pointY":0.5}},"texture":"8414E3B013F9A5AA6A3E085AE0F7E849"}]}]},{"animations":[],"initialState":{"affineTransform":[1,0,0,1,0,0],"masksToBounds":false,"rotation":0,"scale":1,"position":{"pointX":512,"pointY":384},"width":1024,"sublayerTransform":[1,0,0,0,0,1,0,0,0,0,1,0,0,0,0,1],"contentsRect":{"y":0,"x":0,"width":1,"height":1},"opacity":1,"edgeAntialiasingMask":15,"height":768,"hidden":false,"anchorPoint":{"pointX":0.5,"pointY":0.5}},"layers":[{"animations":[],"initialState":{"affineTransform":[1,0,0,1,0,0],"masksToBounds":false,"rotation":0,"scale":1,"position":{"pointX":482,"pointY":381},"width":964,"sublayerTransform":[1,0,0,0,0,1,0,0,0,0,1,0,0,0,0,1],"contentsRect":{"y":0,"x":0,"width":1,"height":1},"opacity":1,"edgeAntialiasingMask":15,"height":762,"hidden":false,"anchorPoint":{"pointX":0.5,"pointY":0.5}},"objectID":"194F9EBE-463B-4D77-97DE-B889A2EC21CE","layers":[{"animations":[],"layers":[],"initialState":{"affineTransform":[1,0,0,1,0,0],"masksToBounds":false,"rotation":0,"scale":1,"position":{"pointX":482,"pointY":381},"width":966,"sublayerTransform":[1,0,0,0,0,1,0,0,0,0,1,0,0,0,0,1],"contentsRect":{"y":0,"x":0,"width":1,"height":1},"opacity":1,"edgeAntialiasingMask":0,"height":764,"hidden":false,"anchorPoint":{"pointX":0.5,"pointY":0.5}},"texture":"1BD2835E22F9C6F1FD62E8522C32F9D7"}]}]},{"animations":[],"initialState":{"affineTransform":[1,0,0,1,0,0],"masksToBounds":false,"rotation":0,"scale":1,"position":{"pointX":512,"pointY":384},"width":1024,"sublayerTransform":[1,0,0,0,0,1,0,0,0,0,1,0,0,0,0,1],"contentsRect":{"y":0,"x":0,"width":1,"height":1},"opacity":1,"edgeAntialiasingMask":15,"height":768,"hidden":false,"anchorPoint":{"pointX":0.5,"pointY":0.5}},"layers":[{"animations":[],"initialState":{"affineTransform":[1,0,0,1,0,0],"masksToBounds":false,"rotation":0,"scale":1,"position":{"pointX":253.1645812988281,"pointY":169.5929565429688},"width":484.3291015625,"sublayerTransform":[1,0,0,0,0,1,0,0,0,0,1,0,0,0,0,1],"contentsRect":{"y":0,"x":0,"width":1,"height":1},"opacity":1,"edgeAntialiasingMask":15,"height":289,"hidden":false,"anchorPoint":{"pointX":0.5,"pointY":0.5}},"objectID":"D8CE3AF1-87F9-403A-ABA6-263FDDBAB4F5","layers":[{"animations":[],"layers":[],"initialState":{"affineTransform":[1,0,0,1,0,0],"masksToBounds":false,"rotation":0,"scale":1,"position":{"pointX":242.4999694824219,"pointY":144.9070434570312},"width":487,"sublayerTransform":[1,0,0,0,0,1,0,0,0,0,1,0,0,0,0,1],"contentsRect":{"y":0,"x":0,"width":1,"height":1},"opacity":1,"edgeAntialiasingMask":0,"height":292,"hidden":true,"anchorPoint":{"pointX":0.5,"pointY":0.5}},"texture":"0708201BFD57950854BA39BE36670832"}]}]},{"animations":[],"initialState":{"affineTransform":[1,0,0,1,0,0],"masksToBounds":false,"rotation":0,"scale":1,"position":{"pointX":512,"pointY":384},"width":1024,"sublayerTransform":[1,0,0,0,0,1,0,0,0,0,1,0,0,0,0,1],"contentsRect":{"y":0,"x":0,"width":1,"height":1},"opacity":1,"edgeAntialiasingMask":15,"height":768,"hidden":false,"anchorPoint":{"pointX":0.5,"pointY":0.5}},"layers":[{"animations":[],"initialState":{"affineTransform":[1,0,0,1,0,0],"masksToBounds":false,"rotation":0,"scale":1,"position":{"pointX":810.2232055664062,"pointY":494.1589050292969},"width":282,"sublayerTransform":[1,0,0,0,0,1,0,0,0,0,1,0,0,0,0,1],"contentsRect":{"y":0,"x":0,"width":1,"height":1},"opacity":1,"edgeAntialiasingMask":15,"height":515.6821899414062,"hidden":false,"anchorPoint":{"pointX":0.5,"pointY":0.5}},"objectID":"80067297-E7D8-4843-BC5E-F2976BBE1970","layers":[{"animations":[],"layers":[],"initialState":{"affineTransform":[1,0,0,1,0,0],"masksToBounds":false,"rotation":0,"scale":1,"position":{"pointX":141.2767944335938,"pointY":257.6821899414062},"width":285,"sublayerTransform":[1,0,0,0,0,1,0,0,0,0,1,0,0,0,0,1],"contentsRect":{"y":0,"x":0,"width":1,"height":1},"opacity":1,"edgeAntialiasingMask":0,"height":518,"hidden":true,"anchorPoint":{"pointX":0.5,"pointY":0.5}},"texture":"03E2A4267C1077634D56A7B4FCEDB452"}]}]},{"animations":[],"initialState":{"affineTransform":[1,0,0,1,0,0],"masksToBounds":false,"rotation":0,"scale":1,"position":{"pointX":512,"pointY":384},"width":1024,"sublayerTransform":[1,0,0,0,0,1,0,0,0,0,1,0,0,0,0,1],"contentsRect":{"y":0,"x":0,"width":1,"height":1},"opacity":1,"edgeAntialiasingMask":15,"height":768,"hidden":false,"anchorPoint":{"pointX":0.5,"pointY":0.5}},"layers":[{"animations":[],"initialState":{"affineTransform":[1,0,0,1,0,0],"masksToBounds":false,"rotation":0,"scale":1,"position":{"pointX":500.58837890625,"pointY":392.5},"width":189,"sublayerTransform":[1,0,0,0,0,1,0,0,0,0,1,0,0,0,0,1],"contentsRect":{"y":0,"x":0,"width":1,"height":1},"opacity":1,"edgeAntialiasingMask":15,"height":134,"hidden":false,"anchorPoint":{"pointX":0.5,"pointY":0.5}},"objectID":"93FCFA40-E74A-44ED-BE2F-F9EA6178C874","layers":[{"animations":[],"layers":[],"initialState":{"affineTransform":[1,0,0,1,0,0],"masksToBounds":false,"rotation":0,"scale":1,"position":{"pointX":89.91162109375,"pointY":71},"width":186,"sublayerTransform":[1,0,0,0,0,1,0,0,0,0,1,0,0,0,0,1],"contentsRect":{"y":0,"x":0,"width":1,"height":1},"opacity":1,"edgeAntialiasingMask":0,"height":113,"hidden":false,"anchorPoint":{"pointX":0.5,"pointY":0.5}},"texture":"07BB6D00D518A96220A4FC58EE8BCBF4"}]}]}]}},{"effects":[{"beginTime":0,"baseLayer":{"animations":[],"initialState":{"affineTransform":[1,0,0,1,0,0],"masksToBounds":true,"rotation":0,"scale":1,"position":{"pointX":512,"pointY":384},"width":1024,"sublayerTransform":[1,0,0,0,0,1,0,0,0,0,1,0,0,0,0,1],"contentsRect":{"y":0,"x":0,"width":1,"height":1},"opacity":1,"edgeAntialiasingMask":0,"height":768,"hidden":false,"anchorPoint":{"pointX":0.5,"pointY":0.5}},"objectID":"0","layers":[{"animations":[],"initialState":{"affineTransform":[1,0,0,1,0,0],"masksToBounds":false,"rotation":0,"scale":1,"position":{"pointX":512,"pointY":384},"width":1024,"sublayerTransform":[1,0,0,0,0,1,0,0,0,0,1,-0.0004922987690640373,0,0,0,1],"contentsRect":{"y":0,"x":0,"width":1,"height":1},"opacity":1,"edgeAntialiasingMask":15,"height":768,"hidden":false,"anchorPoint":{"pointX":0.5,"pointY":0.5}},"layers":[{"animations":[],"layers":[],"initialState":{"affineTransform":[1,0,0,1,0,0],"masksToBounds":false,"rotation":0,"scale":1,"position":{"pointX":512,"pointY":384},"width":1024,"sublayerTransform":[1,0,0,0,0,1,0,0,0,0,1,0,0,0,0,1],"contentsRect":{"y":0,"x":0,"width":1,"height":1},"opacity":1,"edgeAntialiasingMask":0,"height":768,"hidden":false,"anchorPoint":{"pointX":0.5,"pointY":0.5}},"texture":"BE27CFED30023A25174C01549F881949"},{"animations":[{"from":{"scalar":false},"beginTime":0,"repeatCount":0,"fillMode":"both","property":"hidden","duration":0.01,"to":{"scalar":true}}],"layers":[],"initialState":{"affineTransform":[1,0,0,1,0,0],"masksToBounds":false,"rotation":0,"scale":1,"position":{"pointX":512,"pointY":384},"width":1024,"sublayerTransform":[1,0,0,0,0,1,0,0,0,0,1,0,0,0,0,1],"contentsRect":{"y":0,"x":0,"width":1,"height":1},"opacity":1,"edgeAntialiasingMask":0,"height":768,"hidden":false,"anchorPoint":{"pointX":0.5,"pointY":0.5}},"texture":"0B7E82647FE32B8434637900C863EBF3"}]}]},"effects":[],"duration":0.01,"type":"transition","name":"none","objectID":"0"}],"automaticPlay":false,"hyperlinks":[],"accessibility":[{"text":"me3.png","targetRectangle":{"y":236.3178100585938,"x":669.2232055664062,"width":282,"height":515.6821899414062}},{"text":"VS","targetRectangle":{"y":329.5,"x":410.58837890625,"width":180,"height":126}},{"text":"oled.png","targetRectangle":{"y":25.09295654296875,"x":11.00003051757812,"width":484.3291015625,"height":289}}],"baseLayer":{"animations":[],"initialState":{"affineTransform":[1,0,0,1,0,0],"masksToBounds":true,"rotation":0,"scale":1,"position":{"pointX":512,"pointY":384},"width":1024,"sublayerTransform":[1,0,0,0,0,1,0,0,0,0,1,0,0,0,0,1],"contentsRect":{"y":0,"x":0,"width":1,"height":1},"opacity":1,"edgeAntialiasingMask":0,"height":768,"hidden":false,"anchorPoint":{"pointX":0.5,"pointY":0.5}},"objectID":"0","layers":[{"animations":[],"initialState":{"affineTransform":[1,0,0,1,0,0],"masksToBounds":false,"rotation":0,"scale":1,"position":{"pointX":512,"pointY":384},"width":1024,"sublayerTransform":[1,0,0,0,0,1,0,0,0,0,1,-0.0004922987690640373,0,0,0,1],"contentsRect":{"y":0,"x":0,"width":1,"height":1},"opacity":1,"edgeAntialiasingMask":15,"height":768,"hidden":false,"anchorPoint":{"pointX":0.5,"pointY":0.5}},"layers":[{"animations":[],"layers":[],"initialState":{"affineTransform":[1,0,0,1,0,0],"masksToBounds":false,"rotation":0,"scale":1,"position":{"pointX":512,"pointY":384},"width":1024,"sublayerTransform":[1,0,0,0,0,1,0,0,0,0,1,0,0,0,0,1],"contentsRect":{"y":0,"x":0,"width":1,"height":1},"opacity":1,"edgeAntialiasingMask":0,"height":768,"hidden":false,"anchorPoint":{"pointX":0.5,"pointY":0.5}},"texture":"0B7E82647FE32B8434637900C863EBF3"}]}]}}]}